{"help": "https://data.gov.sg/api/3/action/help_show?name=datastore_search", "success": true, "result": {"resource_id": "f7b0f838-7fcb-4ea1-bce5-d855ef50b25a", "fields": [{"type": "int4", "id": "_id"}, {"type": "numeric", "id": "year"}, {"type": "text", "id": "level_1"}, {"type": "numeric", "id": "value"}], "records": [{"_id": 1, "level_1": "Establishments, SSIC 56 - Total Food & Beverage Services", "value": "6871", "year": "2014"}, {"_id": 2, "level_1": "Establishments, SSIC 56 - Total Food & Beverage Services", "value": "7229", "year": "2015"}, {"_id": 3, "level_1": "Establishments, SSIC 56 - Total Food & Beverage Services", "value": "7679", "year": "2016"}], "_links": {"start": "/api/action/datastore_search?limit=5&resource_id=f7b0f838-7fcb-4ea1-bce5-d855ef50b25a", "next": "/api/action/datastore_search?offset=5&limit=5&resource_id=f7b0f838-7fcb-4ea1-bce5-d855ef50b25a"}, "limit": 5, "total": 3}}