{"help": "https://data.gov.sg/api/3/action/help_show?name=datastore_search", "success": true, "result": {"resource_id": "a252963a-e3b5-4dfc-8f84-3c307a6968d6", "fields": [{"type": "int4", "id": "_id"}, {"type": "text", "id": "24-hr_psi"}, {"type": "numeric", "id": "north"}, {"type": "numeric", "id": "south"}, {"type": "numeric", "id": "east"}, {"type": "numeric", "id": "west"}, {"type": "numeric", "id": "central"}, {"type": "int8", "id": "_full_count"}, {"type": "float4", "id": "rank"}], "q": "jones", "records": [], "_links": {"start": "/api/action/datastore_search?q=jones&resource_id=a252963a-e3b5-4dfc-8f84-3c307a6968d6", "next": "/api/action/datastore_search?q=jones&offset=100&resource_id=a252963a-e3b5-4dfc-8f84-3c307a6968d6"}}}